graphlight/__init__.py
graphlight/core.py
graphlight-0.0.2.dist-info/LICENSE
graphlight-0.0.2.dist-info/METADATA
graphlight-0.0.2.dist-info/WHEEL
graphlight-0.0.2.dist-info/top_level.txt
graphlight-0.0.2.dist-info/RECORD
