Metadata-Version: 2.1
Name: graphlight
Version: 0.0.2
Summary: A lightweight graph database library
Home-page: https://github.com/collinparan/graphlight
Author: Collin Paran
Author-email: collin@professai.com
Classifier: Programming Language :: Python :: 3
Classifier: License :: OSI Approved :: Apache Software License
Classifier: Operating System :: OS Independent
Requires-Python: >=3.6
License-File: LICENSE
